README
setup.cfg
setup.py
mzOS.egg-info/PKG-INFO
mzOS.egg-info/SOURCES.txt
mzOS.egg-info/dependency_links.txt
mzOS.egg-info/entry_points.txt
mzOS.egg-info/top_level.txt
mzos/__init__.py
mzos/__main__.py
mzos/annotator.py
mzos/bayesian_inference.py
mzos/clustering.py
mzos/database_finder.py
mzos/exp_design.py
mzos/feature.py
mzos/formula.py
mzos/mass_default.py
mzos/merge_spectra.py
mzos/mongo_db.py
mzos/pathway_enrichment.py
mzos/peakel_clusterer.py
mzos/peaklist_reader.py
mzos/reac.py
mzos/results_exporter.py
mzos/stats.py
mzos/utils.py
mzos/ressources/FRAGMENTS.csv
mzos/ressources/FRAGMENTS_IMS.csv
mzos/ressources/ISO.csv
mzos/ressources/LMSD_20130306_All.tsv
mzos/ressources/NEG_ADDUCTS.csv
mzos/ressources/NEG_ADDUCTS_IMS.csv
mzos/ressources/POS_ADDUCTS.csv
mzos/ressources/POS_ADDUCTS_IMS.csv
mzos/ressources/__init__.py
mzos/ressources/__init__.pyc
mzos/ressources/hmdb.zip
mzos/ressources/lmsd.sqlite
mzos/ressources/lmsd.zip
mzos/ressources/peaks_matrix_NEG.tsv
mzos/ressources/reaction.reac
mzos/scripts/__init__.py
mzos/scripts/get_kegg_reactions.py
mzos/scripts/hmdb_sqlite_creator.py
mzos/scripts/lmsd_sqlite_creator.py
mzos/scripts/mzos_script.py
mzos/tests/__init__.py
mzos/tests/test_database_search.py
mzos/tests/test_integration.py
mzos/tests/test_models.py
mzos/tests/test_peaklist_reader.py
mzos/third_party/__init__.py
mzos/third_party/emass/COPYING
mzos/third_party/emass/ISOTOPE.DAT
mzos/third_party/emass/Makefile
mzos/third_party/emass/README
mzos/third_party/emass/__init__.py
mzos/third_party/emass/__init__.pyc
mzos/third_party/emass/emass.cpp
mzos/third_party/emass/emass.exe
mzos/third_party/emass/emass.h
mzos/third_party/emass/emass.sln
mzos/third_party/emass/emass.vcproj
mzos/third_party/emass/formula.cpp
mzos/third_party/emass/formula.h
mzos/third_party/emass/getopt.cpp
mzos/third_party/emass/getopt.h
mzos/third_party/emass/gmon.out
mzos/third_party/emass/parser.cpp
mzos/third_party/emass/parser.h