Metadata-Version: 1.1
Name: mzOS
Version: 0.1.3
Summary: Heuristic based feature annotations/identifications of LC-MS metabolomics dataset.
Home-page: http://github.com/jerkos/mzOS
Author: Marco Dubois
Author-email: cram@hotmail.fr
License: MIT
Platform: UNKNOWN
Classifier: Development Status :: 3 - Alpha
Classifier: License :: OSI Approved :: MIT License
Classifier: Programming Language :: Python :: 2.7
Classifier: Programming Language :: Python :: 3.3
Classifier: Programming Language :: Python :: 3.4
Classifier: Programming Language :: Python :: 3.5
Classifier: Topic :: Scientific/Engineering :: Bio-Informatics
Requires: bioservices
Requires: scipy
Requires: numpy
Requires: six
Requires: sklearn
Requires: pandas
